mult.v
module mult(
input[2:0] a,
input [2:0] b,
input clk,
input init,
output reg [5:0] result,
output reg done
);
parameter star = 3'b000;
parameter check = 3'b001;
parameter add = 3'b010;
parameter shift = 3'b011;
parameter finish = 3'b100;

reg [5:0]pp;
reg [2:0] state, next_state;

reg[5:0] a_copy,b_copy;



always @ (posedge clk )
begin
		if (init && state == star)
		
			state <= star;
		else
			
				state <= next_state;
	end

always @(*)
begin
  case(state)
     star:begin
     pp = 0;
     a_copy = a;
     b_copy =b;
     next_state = check;
     done = 0;

    
     end
     
    check:begin
      if(b_copy[0] == 0)begin 
      next_state = shift;  
      end
      else begin 
      next_state = add;
      end
      end

      add:begin 
      pp = pp +a_copy;
      next_state = shift;
      end
      shift: begin 

      a_copy = a_copy <<1;
      b_copy = b_copy >> 1;
      if(b_copy == 0)begin
      next_state = finish;
       
      
      end else begin 
      next_state = check;
      end
      end
      finish: begin 
      done <= 1;
      result <= pp;
      next_state = star;
      
      end

      


  
    default: begin
      next_state = star;
    end
  endcase
end

	endmodule

mult_tb.v
`timescale 1ns/1ps


module mult_tb;

reg [2:0] a, b;
reg clk, init;
wire [5:0] result;
wire done;

mult uut (
    .a(a),
    .b(b),
    .clk(clk),
    .init(init),
    .result(result),
    .done(done)
);

initial begin
    $dumpfile("mult.vcd");
    $dumpvars(0, mult_tb);
end

initial begin
    clk = 0;
    forever #5 clk = ~clk;
end

initial begin
    a = 3'b011;
    b = 3'b101;
    init = 1;
    #10;
    init = 0;
    #200;
    a = 3'b111;
    b = 3'b111;
    #200;
    init = 1;
    #10;
    init = 0;
    #10;
    $finish;
end

endmodule

mult.vcd
$date
	Thu Sep 18 23:29:02 2025
$end
$version
	Icarus Verilog
$end
$timescale
	1ps
$end
$scope module mult_tb $end
$var wire 6 ! result [5:0] $end
$var wire 1 " done $end
$var reg 3 # a [2:0] $end
$var reg 3 $ b [2:0] $end
$var reg 1 % clk $end
$var reg 1 & init $end
$scope module uut $end
$var wire 3 ' a [2:0] $end
$var wire 3 ( b [2:0] $end
$var wire 1 % clk $end
$var wire 1 & init $end
$var parameter 3 ) add $end
$var parameter 3 * check $end
$var parameter 3 + finish $end
$var parameter 3 , shift $end
$var parameter 3 - star $end
$var reg 6 . a_copy [5:0] $end
$var reg 6 / b_copy [5:0] $end
$var reg 1 " done $end
$var reg 3 0 next_state [2:0] $end
$var reg 6 1 pp [5:0] $end
$var reg 6 2 result [5:0] $end
$var reg 3 3 state [2:0] $end
$upscope $end
$upscope $end
$enddefinitions $end
$comment Show the parameter values. $end
$dumpall
b0 -
b11 ,
b100 +
b1 *
b10 )
$end
#0
$dumpvars
bx 3
bx 2
bx 1
b0 0
bx /
bx .
b101 (
b11 '
1&
0%
b101 $
b11 #
x"
bx !
$end
#5000
0"
b1 0
b101 /
b11 .
b0 1
b0 3
1%
#10000
0%
0&
#15000
b10 0
b1 3
1%
#20000
0%
#25000
b11 0
b11 1
b10 3
1%
#30000
0%
#35000
b1 0
b10 /
b110 .
b11 3
1%
#40000
0%
#45000
b11 0
b1 3
1%
#50000
0%
#55000
b1 0
b1 /
b1100 .
b11 3
1%
#60000
0%
#65000
b10 0
b1 3
1%
#70000
0%
#75000
b11 0
b1111 1
b10 3
1%
#80000
0%
#85000
b100 0
b0 /
b11000 .
b11 3
1%
#90000
0%
#95000
b1111 !
b1111 2
1"
b0 0
b100 3
1%
#100000
0%
#105000
0"
b1 0
b101 /
b11 .
b0 1
b0 3
1%
#110000
0%
#115000
b10 0
b1 3
1%
#120000
0%
#125000
b11 0
b11 1
b10 3
1%
#130000
0%
#135000
b1 0
b10 /
b110 .
b11 3
1%
#140000
0%
#145000
b11 0
b1 3
1%
#150000
0%
#155000
b1 0
b1 /
b1100 .
b11 3
1%
#160000
0%
#165000
b10 0
b1 3
1%
#170000
0%
#175000
b11 0
b1111 1
b10 3
1%
#180000
0%
#185000
b100 0
b0 /
b11000 .
b11 3
1%
#190000
0%
#195000
1"
b0 0
b100 3
1%
#200000
0%
#205000
0"
b1 0
b101 /
b11 .
b0 1
b0 3
1%
#210000
b111 /
b111 .
0%
b111 $
b111 (
b111 #
b111 '
#215000
b10 0
b1 3
1%
#220000
0%
#225000
b11 0
b111 1
b10 3
1%
#230000
0%
#235000
b1 0
b11 /
b1110 .
b11 3
1%
#240000
0%
#245000
b10 0
b1 3
1%
#250000
0%
#255000
b11 0
b10101 1
b10 3
1%
#260000
0%
#265000
b1 0
b1 /
b11100 .
b11 3
1%
#270000
0%
#275000
b10 0
b1 3
1%
#280000
0%
#285000
b11 0
b110001 1
b10 3
1%
#290000
0%
#295000
b100 0
b0 /
b111000 .
b11 3
1%
#300000
0%
#305000
b110001 !
b110001 2
1"
b0 0
b100 3
1%
#310000
0%
#315000
0"
b1 0
b111 /
b111 .
b0 1
b0 3
1%
#320000
0%
#325000
b10 0
b1 3
1%
#330000
0%
#335000
b11 0
b111 1
b10 3
1%
#340000
0%
#345000
b1 0
b11 /
b1110 .
b11 3
1%
#350000
0%
#355000
b10 0
b1 3
1%
#360000
0%
#365000
b11 0
b10101 1
b10 3
1%
#370000
0%
#375000
b1 0
b1 /
b11100 .
b11 3
1%
#380000
0%
#385000
b10 0
b1 3
1%
#390000
0%
#395000
b11 0
b110001 1
b10 3
1%
#400000
0%
#405000
b100 0
b0 /
b111000 .
b11 3
1%
#410000
0%
1&
#415000
1"
b0 0
b100 3
1%
#420000
0%
0&
#425000
0"
b1 0
b111 /
b111 .
b0 1
b0 3
1%
